embedisualization/__init__.py
embedisualization/embedisualization.py
embedisualization/top_toolbar.py
embedisualization-0.4.dist-info/METADATA
embedisualization-0.4.dist-info/RECORD
embedisualization-0.4.dist-info/WHEEL
embedisualization-0.4.dist-info/top_level.txt
